market_base/__init__.py
market_base/date.py
market_base/db.py
market_base/filesytem.py
market_base/webdriver/__init__.py
market_base/webdriver/category_page.py
market_base/webdriver/list_product.py
market_base/webdriver/market.py
market_base/webdriver/product.py
market_base/webdriver/product_page.py
market_base/webdriver/url.py
emo_market_base-0.0.5.dist-info/LICENSE
emo_market_base-0.0.5.dist-info/METADATA
emo_market_base-0.0.5.dist-info/WHEEL
emo_market_base-0.0.5.dist-info/top_level.txt
emo_market_base-0.0.5.dist-info/RECORD
