Metadata-Version: 2.1
Name: emo_market_base
Version: 0.0.5
Summary: Marketlerden ürünleri kazıma işlemleri için temel pakettir
Home-page: https://github.com/erenmustafaozdal/market-base
Author: Eren Mustafa Özdal
Author-email: eren.060737@gmail.com
License: MIT
Requires-Python: >=3.11
License-File: LICENSE
Requires-Dist: selenium-web-browser
Requires-Dist: emo-cache-db
Requires-Dist: emo-file-system
Requires-Dist: pillow
Requires-Dist: pdf2image
